zaps/__init__.py
zaps/_logr.py
zaps/_utils.py
zaps/eda/__init__.py
zaps/eda/_cat_analysis.py
zaps/eda/_dist.py
zaps/eda/_num_analysis.py
zaps/eda/_outliers.py
zaps/eda/_uni_analysis.py
zaps/tests/__init__.py
zaps/tests/conftest.py
zaps/tests/test_cat_analysis.py
zaps/tests/test_dist.py
zaps/tests/test_num_analysis.py
zaps/tests/test_outliers.py
zaps/tests/test_uni_analysis.py
zaps/tests/plotting/plotting_tests.ipynb
zaps-1.1.dist-info/LICENSE.txt
zaps-1.1.dist-info/METADATA
zaps-1.1.dist-info/WHEEL
zaps-1.1.dist-info/top_level.txt
zaps-1.1.dist-info/RECORD
