Metadata-Version: 2.1
Name: zaps
Version: 1.1
Summary: Low-code Python wrapper for Exploratory Data Analysis
Author: Amr Muhammad YT/@AmMoPy
License: MIT License (MIT)
Project-URL: repository, https://github.com/AmMoPy/zaps
Project-URL: documentation, https://zaps.readthedocs.io/
Keywords: data analysis,data manipulation,eda,exploratory,insights,outliers,visualizations,wrapper,pipeline
Classifier: Intended Audience :: Science/Research
Classifier: Intended Audience :: Education
Classifier: Intended Audience :: End Users/Desktop
Classifier: License :: OSI Approved :: MIT License
Classifier: Operating System :: OS Independent
Classifier: Programming Language :: Python :: 3
Classifier: Programming Language :: Python :: 3.9
Classifier: Programming Language :: Python :: 3.10
Classifier: Programming Language :: Python :: 3.11
Classifier: Topic :: Scientific/Engineering
Classifier: Topic :: Utilities
Classifier: Topic :: Education
Requires-Python: >=3.9
License-File: LICENSE.txt
Requires-Dist: numpy>=1.26.4
Requires-Dist: pandas>=2.2.2
Requires-Dist: seaborn>=0.13.2
Requires-Dist: matplotlib>=3.9.0
Requires-Dist: plotly>=5.22.0
Requires-Dist: statsmodels>=0.14.2
Requires-Dist: scipy>=1.13.1
Requires-Dist: scikit-learn>=1.5.0
Requires-Dist: distfit>=1.8.0
Requires-Dist: tqdm>=4.66.4
Requires-Dist: ipython>=8.12.3
Requires-Dist: packaging>=24.1
Provides-Extra: test
Requires-Dist: pytest>=8.3.3; extra == "test"
Requires-Dist: twine>=5.1.1; extra == "test"
Requires-Dist: sphinx>=8.1.3; extra == "test"
Requires-Dist: sphinx_rtd_theme; extra == "test"
